odoo/addons/base_user_role_history/README.rst
odoo/addons/base_user_role_history/__init__.py
odoo/addons/base_user_role_history/__manifest__.py
odoo/addons/base_user_role_history/i18n/base_user_role_history.pot
odoo/addons/base_user_role_history/i18n/es.po
odoo/addons/base_user_role_history/i18n/fr.po
odoo/addons/base_user_role_history/i18n/fr_BE.po
odoo/addons/base_user_role_history/models/__init__.py
odoo/addons/base_user_role_history/models/base_user_role_line_history.py
odoo/addons/base_user_role_history/models/res_users.py
odoo/addons/base_user_role_history/readme/CONTRIBUTORS.rst
odoo/addons/base_user_role_history/readme/DESCRIPTION.rst
odoo/addons/base_user_role_history/readme/ROADMAP.rst
odoo/addons/base_user_role_history/readme/USAGE.rst
odoo/addons/base_user_role_history/security/base_user_role_line_history.xml
odoo/addons/base_user_role_history/static/description/icon.png
odoo/addons/base_user_role_history/static/description/index.html
odoo/addons/base_user_role_history/tests/__init__.py
odoo/addons/base_user_role_history/tests/test_base_user_role_history.py
odoo/addons/base_user_role_history/views/base_user_role_line_history.xml
odoo/addons/base_user_role_history/views/res_users.xml
odoo13_addon_base_user_role_history-13.0.1.0.1.dev6.dist-info/METADATA
odoo13_addon_base_user_role_history-13.0.1.0.1.dev6.dist-info/WHEEL
odoo13_addon_base_user_role_history-13.0.1.0.1.dev6.dist-info/top_level.txt
odoo13_addon_base_user_role_history-13.0.1.0.1.dev6.dist-info/RECORD
